{
  "$schema": "https://developer.microsoft.com/json-schemas/fabric/item/report/definition/visualContainer/2.7.0/schema.json",
  "name": "547f34fdfad9a3bfb1a9",
  "position": {
    "x": 11.428571428571429,
    "y": 15.714285714285715,
    "z": 0,
    "height": 122.85714285714286,
    "width": 244.28571428571431,
    "tabOrder": 1000
  },
  "visual": {
    "visualType": "slicer",
    "query": {
      "queryState": {
        "Values": {
          "projections": [
            {
              "field": {
                "Column": {
                  "Expression": {
                    "SourceRef": {
                      "Entity": "lnd_offsetprogram"
                    }
                  },
                  "Property": "Program Name"
                }
              },
              "queryRef": "lnd_offsetprogram.Program Name",
              "nativeQueryRef": "Program Name",
              "active": true
            }
          ]
        }
      }
    },
    "objects": {
      "data": [
        {
          "properties": {
            "mode": {
              "expr": {
                "Literal": {
                  "Value": "'Dropdown'"
                }
              }
            },
            "isInvertedSelectionMode": {
              "expr": {
                "Literal": {
                  "Value": "true"
                }
              }
            }
          }
        }
      ],
      "selection": [
        {
          "properties": {
            "selectAllCheckboxEnabled": {
              "expr": {
                "Literal": {
                  "Value": "true"
                }
              }
            }
          }
        }
      ],
      "general": [
        {
          "properties": {
            "filter": {
              "filter": {
                "Version": 2,
                "From": [
                  {
                    "Name": "l",
                    "Entity": "lnd_offsetprogram",
                    "Type": 0
                  }
                ],
                "Where": [
                  {
                    "Condition": {
                      "Not": {
                        "Expression": {
                          "In": {
                            "Expressions": [
                              {
                                "Column": {
                                  "Expression": {
                                    "SourceRef": {
                                      "Source": "l"
                                    }
                                  },
                                  "Property": "Program Name"
                                }
                              }
                            ],
                            "Values": [
                              [
                                {
                                  "Literal": {
                                    "Value": "null"
                                  }
                                }
                              ]
                            ]
                          }
                        }
                      }
                    }
                  }
                ]
              }
            }
          }
        }
      ]
    },
    "syncGroup": {
      "groupName": "Program Name",
      "fieldChanges": true,
      "filterChanges": true
    },
    "drillFilterOtherVisuals": true
  }
}